{"Tester_59818CD2@test,com": {"userName": "Tester_59818CD2", "labels": {"Surfing the internet": 0.0, "Standing": 399.0, "With co-workers": 0.0, "Phone in pocket": 0.0, "Bathing - shower": 56.0, "Bicycling": 369.0, "Stairs - going down": 0.0, "At home": 307.0, "Stairs - going up": 0.0, "Elevator": 0.0, "Drinking (alcohol)": 0.0, "Outside": 74.0, "In class": 0.0, "Drive - I'm a passenger": 0.0, "Dressing": 0.0, "Exercise": 378.0, "Shopping": 0.0, "At a bar": 0.0, "Sitting": 1561.0, "Phone on table": 45.0, "In a car": 76.0, "Running": 9.0, "Phone in hand": 0.0, "Cleaning": 0.0, "Lab work": 0.0, "In a meeting": 0.0, "With friends": 57.0, "At a restaurant": 0.0, "Cooking": 0.0, "At main workplace": 0.0, "Doing laundry": 0.0, "At the gym": 0.0, "Phone in bag": 0.0, "At a party": 0.0, "Eating": 115.0, "Grooming": 0.0, "On a bus": 2.0, "Lying down": 233.0, "At school": 579.0, "Toilet": 0.0, "Walking": 236.0, "Washing dishes": 0.0, "Watching TV": 0.0, "Strolling": 0.0, "Drive - I'm the driver": 0.0, "Sleeping": 63.0, "Talking": 31.0, "Indoors": 714.0, "Computer work": 542.0, "Singing": 0.0, "At the beach": 102.0}, "avatar": "https://api.adorable.io/avatars/250/Tester_59818CD2@test,com.png", "timeRecorded(days)": 6.866793981481481}}