{"Tester_ECECC2AB@test,com": {"userName": "Tester_ECECC2AB", "labels": {"Surfing the internet": 0.0, "Standing": 101.0, "With co-workers": 100.0, "Phone in pocket": 9.0, "Bathing - shower": 0.0, "Bicycling": 0.0, "Stairs - going down": 0.0, "At home": 766.0, "Stairs - going up": 0.0, "Elevator": 0.0, "Drinking (alcohol)": 0.0, "Outside": 120.0, "In class": 35.0, "Drive - I'm a passenger": 0.0, "Dressing": 0.0, "Exercise": 0.0, "Shopping": 15.0, "At a bar": 0.0, "Sitting": 955.0, "Phone on table": 802.0, "In a car": 35.0, "Running": 0.0, "Phone in hand": 0.0, "Cleaning": 0.0, "Lab work": 0.0, "In a meeting": 404.0, "With friends": 777.0, "At a restaurant": 29.0, "Cooking": 79.0, "At main workplace": 1076.0, "Doing laundry": 0.0, "At the gym": 0.0, "Phone in bag": 314.0, "At a party": 0.0, "Eating": 124.0, "Grooming": 0.0, "On a bus": 17.0, "Lying down": 25.0, "At school": 940.0, "Toilet": 14.0, "Walking": 156.0, "Washing dishes": 79.0, "Watching TV": 0.0, "Strolling": 0.0, "Drive - I'm the driver": 35.0, "Sleeping": 25.0, "Talking": 491.0, "Indoors": 236.0, "Computer work": 0.0, "Singing": 35.0, "At the beach": 0.0}, "avatar": "https://api.adorable.io/avatars/250/Tester_ECECC2AB@test,com.png", "timeRecorded(days)": 6.890266203703704}}